[
    {
        "Hull Number": "677",
        "Boat Name": "MYOURI II",
        "Yacht Club": "BYC"
    },
    {
        "Hull Number": "656",
        "Boat Name": "Aurora",
        "Yacht Club": "BYC"
    },
    {
        "Hull Number": "638",
        "Boat Name": "Osprey",
        "Yacht Club": "BHSC"
    },
    {
        "Hull Number": "618",
        "Boat Name": "Wrecking Crew",
        "Yacht Club": "BHSC"
    },
    {
        "Hull Number": "246",
        "Boat Name": "Mr. Krabs",
        "Yacht Club": "BHSC"
    },
    {
        "Hull Number": "37",
        "Boat Name": "Windependence",
        "Yacht Club": "BHSC"
    },
    {
        "Hull Number": "423",
        "Boat Name": "Southbound",
        "Yacht Club": "SSC"
    },
    {
        "Hull Number": "376",
        "Boat Name": "Whistler",
        "Yacht Club": "NCYC"
    },
    {
        "Hull Number": "145",
        "Boat Name": "Kashmir",
        "Yacht Club": "NCYC"
    },
    {
        "Hull Number": "118",
        "Boat Name": "Relentless",
        "Yacht Club": "NCYC"
    },
    {
        "Hull Number": "148",
        "Boat Name": "Wish",
        "Yacht Club": "GRSC"
    },
    {
        "Hull Number": "123",
        "Boat Name": "Good Lookin",
        "Yacht Club": ""
    },
    {
        "Hull Number": "10",
        "Boat Name": "Zamboni",
        "Yacht Club": ""
    },
    {
        "Hull Number": "393",
        "Boat Name": "Ovation",
        "Yacht Club": "EYC"
    },
    {
        "Hull Number": "261",
        "Boat Name": "Unbridled",
        "Yacht Club": "EYC"
    },
    {
        "Hull Number": "208",
        "Boat Name": "Sling Shot",
        "Yacht Club": "EYC"
    },
    {
        "Hull Number": "144",
        "Boat Name": "Fall Line",
        "Yacht Club": "EYC"
    },
    {
        "Hull Number": "91",
        "Boat Name": "Trio",
        "Yacht Club": "EYC"
    },
    {
        "Hull Number": "77",
        "Boat Name": "Dark N Stormy",
        "Yacht Club": "EYC"
    },
    {
        "Hull Number": "72",
        "Boat Name": "Highlander",
        "Yacht Club": "EYC"
    }
]